texteditor/__init__.py
texteditor-1.4.1.dist-info/METADATA
texteditor-1.4.1.dist-info/MIT-LICENSE
texteditor-1.4.1.dist-info/WHEEL
texteditor-1.4.1.dist-info/top_level.txt
texteditor-1.4.1.dist-info/RECORD
