Metadata-Version: 2.1
Name: texteditor
Version: 1.4.1
Summary: Like webbrowser, but for the text editor.
Home-page: https://github.com/jpsca/texteditor
Author: Juan-Pablo Scaletti
Author-email: juanpablo@jpscaletti.com
License: MIT
Project-URL: Issue tracker, https://github.com/jpsca/texteditor/issues
Classifier: Development Status :: 5 - Production/Stable
Classifier: Intended Audience :: Developers
Classifier: License :: OSI Approved :: Apache Software License
Requires-Python: <4.0,>=3.5
Provides-Extra: test
Provides-Extra: dev
License-File: MIT-LICENSE
